{"service":"dynatrace","types":{"azurerm_dynatrace_monitor":{"attrs":[{"n":"location","t":"string","r":1},{"n":"marketplace_subscription","t":"string","r":1},{"n":"name","t":"string","r":1},{"n":"resource_group_name","t":"string","r":1},{"n":"monitoring_enabled","t":"bool"},{"n":"tags","t":"map"}],"blocks":[{"n":"environment_properties","m":"list","attrs":[],"blocks":[{"n":"environment_info","m":"list","attrs":[{"n":"environment_id","t":"string","r":1}],"blocks":[]}]},{"n":"identity","m":"single","attrs":[{"n":"type","t":"string","r":1}],"blocks":[]},{"n":"plan","m":"single","attrs":[{"n":"plan","t":"string","r":1},{"n":"billing_cycle","t":"string"},{"n":"usage_type","t":"string"}],"blocks":[]},{"n":"user","m":"single","attrs":[{"n":"email","t":"string","r":1},{"n":"first_name","t":"string","r":1},{"n":"last_name","t":"string","r":1},{"n":"country","t":"string"},{"n":"phone_number","t":"string"}],"blocks":[]}]},"azurerm_dynatrace_tag_rules":{"attrs":[{"n":"monitor_id","t":"string","r":1},{"n":"name","t":"string","r":1}],"blocks":[{"n":"log_rule","m":"single","attrs":[{"n":"send_activity_logs_enabled","t":"bool"},{"n":"send_azure_active_directory_logs_enabled","t":"bool"},{"n":"send_subscription_logs_enabled","t":"bool"}],"blocks":[{"n":"filtering_tag","m":"list","attrs":[{"n":"action","t":"string","r":1},{"n":"name","t":"string","r":1},{"n":"value","t":"string","r":1}],"blocks":[]}]},{"n":"metric_rule","m":"single","attrs":[{"n":"sending_metrics_enabled","t":"bool"}],"blocks":[{"n":"filtering_tag","m":"list","attrs":[{"n":"action","t":"string","r":1},{"n":"name","t":"string","r":1},{"n":"value","t":"string","r":1}],"blocks":[]}]}]}}}