{"service":"sql","types":{"azurerm_mssql_database":{"attrs":[{"n":"name","t":"string","r":1},{"n":"server_id","t":"string","r":1},{"n":"auto_pause_delay_in_minutes","t":"json"},{"n":"collation","t":"string"},{"n":"create_mode","t":"string"},{"n":"creation_source_database_id","t":"string"},{"n":"elastic_pool_id","t":"string"},{"n":"enclave_type","t":"string"},{"n":"geo_backup_enabled","t":"bool"},{"n":"ledger_enabled","t":"bool"},{"n":"license_type","t":"string"},{"n":"maintenance_configuration_name","t":"string"},{"n":"max_size_gb","t":"json"},{"n":"min_capacity","t":"json"},{"n":"read_replica_count","t":"json"},{"n":"read_scale","t":"bool"},{"n":"recover_database_id","t":"string"},{"n":"recovery_point_id","t":"string"},{"n":"restore_dropped_database_id","t":"string"},{"n":"restore_long_term_retention_backup_id","t":"string"},{"n":"restore_point_in_time","t":"string"},{"n":"sample_name","t":"string"},{"n":"secondary_type","t":"string"},{"n":"sku_name","t":"string"},{"n":"storage_account_type","t":"string"},{"n":"tags","t":"map"},{"n":"transparent_data_encryption_enabled","t":"bool"},{"n":"transparent_data_encryption_key_automatic_rotation_enabled","t":"bool"},{"n":"transparent_data_encryption_key_vault_key_id","t":"string"},{"n":"zone_redundant","t":"bool"}],"blocks":[{"n":"identity","m":"single","attrs":[{"n":"identity_ids","t":"list","r":1},{"n":"type","t":"string","r":1}],"blocks":[]},{"n":"import","m":"single","attrs":[{"n":"administrator_login","t":"string","r":1},{"n":"administrator_login_password","t":"string","r":1,"s":1},{"n":"authentication_type","t":"string","r":1},{"n":"storage_key","t":"string","r":1,"s":1},{"n":"storage_key_type","t":"string","r":1},{"n":"storage_uri","t":"string","r":1},{"n":"storage_account_id","t":"string"}],"blocks":[]},{"n":"long_term_retention_policy","m":"single","attrs":[{"n":"immutable_backups_enabled","t":"bool"},{"n":"monthly_retention","t":"string"},{"n":"week_of_year","t":"json"},{"n":"weekly_retention","t":"string"},{"n":"yearly_retention","t":"string"}],"blocks":[]},{"n":"short_term_retention_policy","m":"single","attrs":[{"n":"retention_days","t":"json","r":1},{"n":"backup_interval_in_hours","t":"json"}],"blocks":[]},{"n":"threat_detection_policy","m":"single","attrs":[{"n":"disabled_alerts","t":"list"},{"n":"email_account_admins","t":"string"},{"n":"email_addresses","t":"list"},{"n":"retention_days","t":"json"},{"n":"state","t":"string"},{"n":"storage_account_access_key","t":"string","s":1},{"n":"storage_endpoint","t":"string"}],"blocks":[]}]},"azurerm_mssql_elasticpool":{"attrs":[{"n":"location","t":"string","r":1},{"n":"name","t":"string","r":1},{"n":"resource_group_name","t":"string","r":1},{"n":"server_name","t":"string","r":1},{"n":"enclave_type","t":"string"},{"n":"high_availability_replica_count","t":"json"},{"n":"license_type","t":"string"},{"n":"maintenance_configuration_name","t":"string"},{"n":"max_size_bytes","t":"json"},{"n":"max_size_gb","t":"json"},{"n":"tags","t":"map"},{"n":"zone_redundant","t":"bool"}],"blocks":[{"n":"per_database_settings","m":"single","attrs":[{"n":"max_capacity","t":"json","r":1},{"n":"min_capacity","t":"json","r":1}],"blocks":[]},{"n":"sku","m":"single","attrs":[{"n":"capacity","t":"json","r":1},{"n":"name","t":"string","r":1},{"n":"tier","t":"string","r":1},{"n":"family","t":"string"}],"blocks":[]}]},"azurerm_mssql_failover_group":{"attrs":[{"n":"name","t":"string","r":1},{"n":"server_id","t":"string","r":1},{"n":"databases","t":"list"},{"n":"readonly_endpoint_failover_policy_enabled","t":"bool"},{"n":"tags","t":"map"}],"blocks":[{"n":"partner_server","m":"list","attrs":[{"n":"id","t":"string","r":1}],"blocks":[],"min":1},{"n":"read_write_endpoint_failover_policy","m":"single","attrs":[{"n":"mode","t":"string","r":1},{"n":"grace_minutes","t":"json"}],"blocks":[]}]},"azurerm_mssql_job_agent":{"attrs":[{"n":"database_id","t":"string","r":1},{"n":"location","t":"string","r":1},{"n":"name","t":"string","r":1},{"n":"sku","t":"string"},{"n":"tags","t":"map"}],"blocks":[{"n":"identity","m":"single","attrs":[{"n":"identity_ids","t":"list","r":1},{"n":"type","t":"string","r":1}],"blocks":[]}]},"azurerm_mssql_managed_database":{"attrs":[{"n":"managed_instance_id","t":"string","r":1},{"n":"name","t":"string","r":1},{"n":"short_term_retention_days","t":"json"},{"n":"tags","t":"map"}],"blocks":[{"n":"long_term_retention_policy","m":"single","attrs":[{"n":"monthly_retention","t":"string"},{"n":"week_of_year","t":"json"},{"n":"weekly_retention","t":"string"},{"n":"yearly_retention","t":"string"}],"blocks":[]},{"n":"point_in_time_restore","m":"single","attrs":[{"n":"restore_point_in_time","t":"string","r":1},{"n":"source_database_id","t":"string","r":1}],"blocks":[]}]},"azurerm_mssql_managed_instance":{"attrs":[{"n":"license_type","t":"string","r":1},{"n":"location","t":"string","r":1},{"n":"name","t":"string","r":1},{"n":"resource_group_name","t":"string","r":1},{"n":"sku_name","t":"string","r":1},{"n":"storage_size_in_gb","t":"json","r":1},{"n":"subnet_id","t":"string","r":1},{"n":"vcores","t":"json","r":1},{"n":"administrator_login","t":"string"},{"n":"administrator_login_password","t":"string","s":1},{"n":"collation","t":"string"},{"n":"database_format","t":"string"},{"n":"dns_zone_partner_id","t":"string"},{"n":"general_purpose_v2_enabled","t":"bool"},{"n":"hybrid_secondary_usage","t":"string"},{"n":"maintenance_configuration_name","t":"string"},{"n":"minimum_tls_version","t":"string"},{"n":"proxy_override","t":"string"},{"n":"public_data_endpoint_enabled","t":"bool"},{"n":"service_principal_type","t":"string"},{"n":"storage_account_type","t":"string"},{"n":"storage_iops","t":"json"},{"n":"tags","t":"map"},{"n":"timezone_id","t":"string"},{"n":"zone_redundant_enabled","t":"bool"}],"blocks":[{"n":"azure_active_directory_administrator","m":"single","attrs":[{"n":"login_username","t":"string","r":1},{"n":"object_id","t":"string","r":1},{"n":"principal_type","t":"string","r":1},{"n":"azuread_authentication_only_enabled","t":"bool"},{"n":"tenant_id","t":"string"}],"blocks":[]},{"n":"identity","m":"single","attrs":[{"n":"type","t":"string","r":1},{"n":"identity_ids","t":"list"}],"blocks":[]}]},"azurerm_mssql_server":{"attrs":[{"n":"location","t":"string","r":1},{"n":"name","t":"string","r":1},{"n":"resource_group_name","t":"string","r":1},{"n":"version","t":"string","r":1},{"n":"administrator_login","t":"string"},{"n":"administrator_login_password","t":"string","s":1},{"n":"administrator_login_password_wo","t":"string","s":1},{"n":"administrator_login_password_wo_version","t":"json"},{"n":"connection_policy","t":"string"},{"n":"express_vulnerability_assessment_enabled","t":"bool"},{"n":"minimum_tls_version","t":"string"},{"n":"outbound_network_restriction_enabled","t":"bool"},{"n":"primary_user_assigned_identity_id","t":"string"},{"n":"public_network_access_enabled","t":"bool"},{"n":"tags","t":"map"},{"n":"transparent_data_encryption_key_vault_key_id","t":"string"}],"blocks":[{"n":"azuread_administrator","m":"single","attrs":[{"n":"login_username","t":"string","r":1},{"n":"object_id","t":"string","r":1},{"n":"azuread_authentication_only","t":"bool"},{"n":"tenant_id","t":"string"}],"blocks":[],"min":1},{"n":"identity","m":"single","attrs":[{"n":"type","t":"string","r":1},{"n":"identity_ids","t":"list"}],"blocks":[]}]},"azurerm_mssql_virtual_machine":{"attrs":[{"n":"virtual_machine_id","t":"string","r":1},{"n":"r_services_enabled","t":"bool"},{"n":"sql_connectivity_port","t":"json"},{"n":"sql_connectivity_type","t":"string"},{"n":"sql_connectivity_update_password","t":"string","s":1},{"n":"sql_connectivity_update_username","t":"string","s":1},{"n":"sql_license_type","t":"string"},{"n":"sql_virtual_machine_group_id","t":"string"},{"n":"tags","t":"map"}],"blocks":[{"n":"assessment","m":"single","attrs":[{"n":"enabled","t":"bool"},{"n":"run_immediately","t":"bool"}],"blocks":[{"n":"schedule","m":"single","attrs":[{"n":"day_of_week","t":"string","r":1},{"n":"start_time","t":"string","r":1},{"n":"monthly_occurrence","t":"json"},{"n":"weekly_interval","t":"json"}],"blocks":[]}]},{"n":"auto_backup","m":"single","attrs":[{"n":"retention_period_in_days","t":"json","r":1},{"n":"storage_account_access_key","t":"string","r":1},{"n":"storage_blob_endpoint","t":"string","r":1},{"n":"encryption_password","t":"string","s":1},{"n":"system_databases_backup_enabled","t":"bool"}],"blocks":[{"n":"manual_schedule","m":"single","attrs":[{"n":"full_backup_frequency","t":"string","r":1},{"n":"full_backup_start_hour","t":"json","r":1},{"n":"full_backup_window_in_hours","t":"json","r":1},{"n":"log_backup_frequency_in_minutes","t":"json","r":1},{"n":"days_of_week","t":"list"}],"blocks":[]}]},{"n":"auto_patching","m":"single","attrs":[{"n":"day_of_week","t":"string","r":1},{"n":"maintenance_window_duration_in_minutes","t":"json","r":1},{"n":"maintenance_window_starting_hour","t":"json","r":1}],"blocks":[]},{"n":"key_vault_credential","m":"single","attrs":[{"n":"key_vault_url","t":"string","r":1,"s":1},{"n":"name","t":"string","r":1},{"n":"service_principal_name","t":"string","r":1,"s":1},{"n":"service_principal_secret","t":"string","r":1,"s":1}],"blocks":[]},{"n":"sql_instance","m":"single","attrs":[{"n":"adhoc_workloads_optimization_enabled","t":"bool"},{"n":"collation","t":"string"},{"n":"instant_file_initialization_enabled","t":"bool"},{"n":"lock_pages_in_memory_enabled","t":"bool"},{"n":"max_dop","t":"json"},{"n":"max_server_memory_mb","t":"json"},{"n":"min_server_memory_mb","t":"json"}],"blocks":[]},{"n":"storage_configuration","m":"single","attrs":[{"n":"disk_type","t":"string","r":1},{"n":"storage_workload_type","t":"string","r":1},{"n":"system_db_on_data_disk_enabled","t":"bool"}],"blocks":[{"n":"data_settings","m":"single","attrs":[{"n":"default_file_path","t":"string","r":1},{"n":"luns","t":"json","r":1}],"blocks":[]},{"n":"log_settings","m":"single","attrs":[{"n":"default_file_path","t":"string","r":1},{"n":"luns","t":"json","r":1}],"blocks":[]},{"n":"temp_db_settings","m":"single","attrs":[{"n":"default_file_path","t":"string","r":1},{"n":"luns","t":"json","r":1},{"n":"data_file_count","t":"json"},{"n":"data_file_growth_in_mb","t":"json"},{"n":"data_file_size_mb","t":"json"},{"n":"log_file_growth_mb","t":"json"},{"n":"log_file_size_mb","t":"json"}],"blocks":[]}]},{"n":"wsfc_domain_credential","m":"single","attrs":[{"n":"cluster_bootstrap_account_password","t":"string","r":1,"s":1},{"n":"cluster_operator_account_password","t":"string","r":1,"s":1},{"n":"sql_service_account_password","t":"string","r":1,"s":1}],"blocks":[]}]},"azurerm_mssql_virtual_machine_group":{"attrs":[{"n":"location","t":"string","r":1},{"n":"name","t":"string","r":1},{"n":"resource_group_name","t":"string","r":1},{"n":"sql_image_offer","t":"string","r":1},{"n":"sql_image_sku","t":"string","r":1},{"n":"tags","t":"map"}],"blocks":[{"n":"wsfc_domain_profile","m":"single","attrs":[{"n":"cluster_subnet_type","t":"string","r":1},{"n":"fqdn","t":"string","r":1},{"n":"cluster_bootstrap_account_name","t":"string"},{"n":"cluster_operator_account_name","t":"string"},{"n":"organizational_unit_path","t":"string"},{"n":"sql_service_account_name","t":"string"},{"n":"storage_account_primary_key","t":"string","s":1},{"n":"storage_account_url","t":"string"}],"blocks":[]}]}}}